Metadata-Version: 2.1
Name: tabular-dict
Version: 0.0.6
Summary: UNKNOWN
Home-page: https://github.com/rgcalsaverini/tabular-dict
Author: Rui Calsaverini
License: UNKNOWN
Platform: UNKNOWN
